setup.py
everton/__init__.py
everton/config.py
everton/everton.py
everton.egg-info/PKG-INFO
everton.egg-info/SOURCES.txt
everton.egg-info/dependency_links.txt
everton.egg-info/entry_points.txt
everton.egg-info/requires.txt
everton.egg-info/top_level.txt