Metadata-Version: 1.0
Name: everton
Version: 0.5
Summary: Evernote command line tool
Home-page: https://github.com/ngc224/everton
Author: Yoshihiko Nishida
Author-email: nishida@ngc224.org
License: UNKNOWN
Platform: UNKNOWN
